csvcli/__init__.py
csvcli/cli.py
csvcli/functions.py
show/__init__.py
show/show.py
csvcli-1.0.2.dist-info/METADATA
csvcli-1.0.2.dist-info/WHEEL
csvcli-1.0.2.dist-info/dependency_links.txt
csvcli-1.0.2.dist-info/entry_points.txt
csvcli-1.0.2.dist-info/top_level.txt
csvcli-1.0.2.dist-info/RECORD
