Metadata-Version: 2.1
Name: csvcli
Version: 1.0.2
Summary: A light-weight command-line tool to browse and query CSV, Excel and Apache Parquet files, regardless of their size.
Home-page: https://github.com/IgnacioMB/csvcli
Author: Ignacio Marin
Author-email: ignacio.marin@holidu.com
License: GNU GPLv3
Download-URL: https://github.com/IgnacioMB/csvcli/archive/main.tar.gz
Platform: UNKNOWN
Classifier: License :: OSI Approved :: GNU General Public License v3 or later (GPLv3+)
Classifier: Programming Language :: Python :: 3.7
Requires-Python: >=3.7
Requires-Dist: click
Requires-Dist: pandas
Requires-Dist: pyarrow (==2.0.0)
Requires-Dist: fastparquet
Requires-Dist: tabulate
Requires-Dist: pandasql
Requires-Dist: xlrd
Requires-Dist: openpyxl
Requires-Dist: numpy
Requires-Dist: wcwidth
